streamlit_app/__init__.py
streamlit_app/main.py
streamlit_test/__init__.py
streamlit_test/globals.py
amzn_project_c_dock_app-1.1.dist-info/METADATA
amzn_project_c_dock_app-1.1.dist-info/WHEEL
amzn_project_c_dock_app-1.1.dist-info/top_level.txt
amzn_project_c_dock_app-1.1.dist-info/RECORD
