Metadata-Version: 2.4
Name: amzn-project-c-dock-app
Version: 1.1
Classifier: Programming Language :: Python :: 3.11
Requires-Python: >=3.11
Requires-Dist: streamlit==1.47.0
Requires-Dist: boto3>=1.24.13
Requires-Dist: filelock==3.14.0
Requires-Dist: numpy<2.0.0,>=1.24.0
Requires-Dist: pyarrow<15.0.0,>=7.0
Requires-Dist: pillow==11.2.1
Provides-Extra: testing
Requires-Dist: coverage[toml]; extra == "testing"
Requires-Dist: pytest>=7; extra == "testing"
Requires-Dist: pytest-cov; extra == "testing"
Requires-Dist: pytest-xdist==3.5.0; extra == "testing"
Provides-Extra: dev
Requires-Dist: black; extra == "dev"
Requires-Dist: coverage[toml]; extra == "dev"
Requires-Dist: flake8; extra == "dev"
Requires-Dist: isort; extra == "dev"
Requires-Dist: mypy; extra == "dev"
Requires-Dist: tox>=4; extra == "dev"
Requires-Dist: twine==5.0.0; extra == "dev"
